mcp_server_baidu_maps/__init__.py
mcp_server_baidu_maps/__main__.py
mcp_server_baidu_maps/map.py
mcp_server_baidu_maps_enhanced-1.0.0.dist-info/licenses/LICENSE
mcp_server_baidu_maps_enhanced-1.0.0.dist-info/METADATA
mcp_server_baidu_maps_enhanced-1.0.0.dist-info/WHEEL
mcp_server_baidu_maps_enhanced-1.0.0.dist-info/entry_points.txt
mcp_server_baidu_maps_enhanced-1.0.0.dist-info/top_level.txt
mcp_server_baidu_maps_enhanced-1.0.0.dist-info/RECORD
