Metadata-Version: 2.4
Name: mcp-server-baidu-maps-enhanced
Version: 1.0.0
Summary: MCP Server Baidu Maps Enhanced - HTTP call Baidu Map API for MCP
Author-email: Feng Rongquan <kirifeng@example.com>
License: MIT
Project-URL: Homepage, https://github.com/baidu-maps/mcp
Project-URL: Repository, https://github.com/baidu-maps/mcp
Project-URL: Bug Reports, https://github.com/baidu-maps/mcp/issues
Keywords: http,mcp,map,baidu,baidu-maps,fastmcp
Requires-Python: >=3.11
License-File: LICENSE
Requires-Dist: mcp[cli]>=1.9.0
Requires-Dist: httpx>=0.27.0
Dynamic: license-file
